MANIFEST.in
README.md
setup.py
imm_case_model.egg-info/PKG-INFO
imm_case_model.egg-info/SOURCES.txt
imm_case_model.egg-info/dependency_links.txt
imm_case_model.egg-info/requires.txt
imm_case_model.egg-info/top_level.txt
model/__init__.py
model/bcpnp/__init__.py
model/bcpnp/companyinfo.py
model/bcpnp/data.py
model/bcpnp/employeetraining.py
model/bcpnp/employertraining.py
model/bcpnp/jobdescription.py
model/bcpnp/jobofferform.py
model/bcpnp/recommendationletter.py
model/bcpnp/repform.py
model/common/__init__.py
model/common/address.py
model/common/advertisement.py
model/common/commonmodel.py
model/common/contact.py
model/common/convert.py
model/common/cor.py
model/common/educationbase.py
model/common/employerbase.py
model/common/employmentbase.py
model/common/employmenthistory.py
model/common/errordict.py
model/common/formmodel.py
model/common/id.py
model/common/jobofferbase.py
model/common/jobposition.py
model/common/language.py
model/common/mixins.py
model/common/person.py
model/common/phone.py
model/common/pr.py
model/common/rcic.py
model/common/tr.py
model/common/trperson.py
model/common/utils.py
model/common/validation.py
model/common/wordmaker.py
model/common/xmlfiller.py
model/common/xmlmaker.py
model/data/__init__.py
model/data/city.py
model/data/country.py
model/data/language.py
model/data/other.py
model/experience/__init__.py
model/experience/ec.py
model/experience/ecdata.py
model/experience/resume.py
model/experience/resumedata.py
model/lmia/__init__.py
model/lmia/data.py
model/lmia/employertraining.py
model/lmia/stage1.py
model/lmia/stage2.py
model/lmia/stage3.py
model/lmia/submissionletter.py
model/pr/__init__.py
model/pr/m0008.py
model/pr/m5406.py
model/pr/m5562.py
model/pr/m5669.py
model/recruit/__init__.py
model/recruit/jobad.py
model/recruit/jobaddata.py
model/recruit/joboffer.py
model/recruit/jobofferdata.py
model/recruit/recruitmentsummary.py
model/template/excel/bcpnp.xlsx
model/template/excel/er.xlsx
model/template/excel/lmia.xlsx
model/template/excel/pa.xlsx
model/template/excel/pr.xlsx
model/template/excel/recruitment.xlsx
model/template/excel/rep.xlsx
model/template/excel/tr.xlsx
